{
  "amtabk": null,
  "ausfertigung_datum": "1970-01-30",
  "bjnr": "BJNR001430970",
  "eli": null,
  "gii_slug": "finausglg1970dv_1",
  "ingested_at": "2026-04-17T15:21:20Z",
  "jurabk": "FinAusglG1970DV 1",
  "schema_version": "v1",
  "source_hashes": {
    "source_xml_sha256": "38916dbba7cc0785ab22aa3ca7de25d45e0f537cce62d39a487a18889a140666"
  },
  "source_urls": {
    "gii_html": "https://www.gesetze-im-internet.de/finausglg1970dv_1/",
    "gii_xml_zip": "https://www.gesetze-im-internet.de/finausglg1970dv_1/xml.zip"
  },
  "stand_datum": null,
  "standangabe": [],
  "title": "Erste Verordnung zur Durchführung des Gesetzes über den Finanzausgleich zwischen Bund und Ländern",
  "tooling_version": "gesetze-corpus-tools@0.1.0"
}
