{
  "amtabk": null,
  "ausfertigung_datum": "2002-06-07",
  "bjnr": "BJNR180300002",
  "eli": null,
  "gii_slug": "versorgausglanglfaktorbek",
  "jurabk": "VersorgAusglAnglFaktorBek",
  "schema_version": "v2",
  "section_counts": {},
  "source_hashes": {
    "source_xml_sha256": "83a1212e100f9a24e893e8d40fa5acf091b45d37247ed7631956b15bc6661115"
  },
  "source_urls": {
    "gii_html": "https://www.gesetze-im-internet.de/versorgausglanglfaktorbek/",
    "gii_xml_zip": "https://www.gesetze-im-internet.de/versorgausglanglfaktorbek/xml.zip"
  },
  "stand_datum": null,
  "standangabe": [],
  "title": "Bekanntmachung der Angleichungsfaktoren für den Versorgungsausgleich in der Rentenversicherung",
  "tooling_version": "gesetze-corpus-tools@0.2.0"
}
