{
  "bjnr": "BJNR005050966",
  "schema_version": "v1",
  "sections": [
    {
      "breadcrumb": [],
      "file": "paragraphs/0001.md",
      "heading": "Vollzugseinrichtungen",
      "number": "§ 1",
      "type": "paragraph"
    },
    {
      "breadcrumb": [],
      "file": "paragraphs/0002.md",
      "heading": "Leitung des Vollzuges",
      "number": "§ 2",
      "type": "paragraph"
    },
    {
      "breadcrumb": [],
      "file": "paragraphs/0003.md",
      "heading": "Mitarbeiter",
      "number": "§ 3",
      "type": "paragraph"
    },
    {
      "breadcrumb": [],
      "file": "paragraphs/0004.md",
      "heading": "Nachdrückliche Vollstreckung",
      "number": "§ 4",
      "type": "paragraph"
    },
    {
      "breadcrumb": [],
      "file": "paragraphs/0005.md",
      "heading": "Aufnahme",
      "number": "§ 5",
      "type": "paragraph"
    },
    {
      "breadcrumb": [],
      "file": "paragraphs/0006.md",
      "heading": "Unterbringung",
      "number": "§ 6",
      "type": "paragraph"
    },
    {
      "breadcrumb": [],
      "file": "paragraphs/0007.md",
      "heading": "Persönlichkeitserforschung",
      "number": "§ 7",
      "type": "paragraph"
    },
    {
      "breadcrumb": [],
      "file": "paragraphs/0008.md",
      "heading": "Behandlung",
      "number": "§ 8",
      "type": "paragraph"
    },
    {
      "breadcrumb": [],
      "file": "paragraphs/0009.md",
      "heading": "Verhaltensvorschriften",
      "number": "§ 9",
      "type": "paragraph"
    },
    {
      "breadcrumb": [],
      "file": "paragraphs/0010.md",
      "heading": "Erziehungsarbeit",
      "number": "§ 10",
      "type": "paragraph"
    },
    {
      "breadcrumb": [],
      "file": "paragraphs/0011.md",
      "heading": "Arbeit und Ausbildung",
      "number": "§ 11",
      "type": "paragraph"
    },
    {
      "breadcrumb": [],
      "file": "paragraphs/0012.md",
      "heading": "Lebenshaltung",
      "number": "§ 12",
      "type": "paragraph"
    },
    {
      "breadcrumb": [],
      "file": "paragraphs/0013.md",
      "heading": "",
      "number": "§ 13",
      "type": "paragraph"
    },
    {
      "breadcrumb": [],
      "file": "paragraphs/0014.md",
      "heading": "",
      "number": "§ 14",
      "type": "paragraph"
    },
    {
      "breadcrumb": [],
      "file": "paragraphs/0015.md",
      "heading": "",
      "number": "§ 15",
      "type": "paragraph"
    },
    {
      "breadcrumb": [],
      "file": "paragraphs/0016.md",
      "heading": "Sport",
      "number": "§ 16",
      "type": "paragraph"
    },
    {
      "breadcrumb": [],
      "file": "paragraphs/0017.md",
      "heading": "Gesundheitspflege",
      "number": "§ 17",
      "type": "paragraph"
    },
    {
      "breadcrumb": [],
      "file": "paragraphs/0018.md",
      "heading": "Freizeit",
      "number": "§ 18",
      "type": "paragraph"
    },
    {
      "breadcrumb": [],
      "file": "paragraphs/0019.md",
      "heading": "Seelsorge",
      "number": "§ 19",
      "type": "paragraph"
    },
    {
      "breadcrumb": [],
      "file": "paragraphs/0020.md",
      "heading": "Verkehr mit der Außenwelt",
      "number": "§ 20",
      "type": "paragraph"
    },
    {
      "breadcrumb": [],
      "file": "paragraphs/0021.md",
      "heading": "Ausgang und Ausführung",
      "number": "§ 21",
      "type": "paragraph"
    },
    {
      "breadcrumb": [],
      "file": "paragraphs/0022.md",
      "heading": "Sicherungsmaßnahmen",
      "number": "§ 22",
      "type": "paragraph"
    },
    {
      "breadcrumb": [],
      "file": "paragraphs/0023.md",
      "heading": "Hausstrafen",
      "number": "§ 23",
      "type": "paragraph"
    },
    {
      "breadcrumb": [],
      "file": "paragraphs/0024.md",
      "heading": "Bitten und Beschwerden",
      "number": "§ 24",
      "type": "paragraph"
    },
    {
      "breadcrumb": [],
      "file": "paragraphs/0025.md",
      "heading": "Zeitpunkt der Aufnahme und der Entlassung",
      "number": "§ 25",
      "type": "paragraph"
    },
    {
      "breadcrumb": [],
      "file": "paragraphs/0026.md",
      "heading": "Fürsorge für die Zeit nach der Entlassung",
      "number": "§ 26",
      "type": "paragraph"
    },
    {
      "breadcrumb": [],
      "file": "paragraphs/0027.md",
      "heading": "Schlußbericht",
      "number": "§ 27",
      "type": "paragraph"
    },
    {
      "breadcrumb": [],
      "file": "paragraphs/0028.md",
      "heading": "",
      "number": "§ 28",
      "type": "paragraph"
    },
    {
      "breadcrumb": [],
      "file": "paragraphs/0029.md",
      "heading": "",
      "number": "§ 29",
      "type": "paragraph"
    },
    {
      "breadcrumb": [],
      "file": "paragraphs/0030.md",
      "heading": "Heranwachsende",
      "number": "§ 30",
      "type": "paragraph"
    },
    {
      "breadcrumb": [],
      "file": "paragraphs/0031.md",
      "heading": "",
      "number": "§ 31",
      "type": "paragraph"
    },
    {
      "breadcrumb": [],
      "file": "paragraphs/0032.md",
      "heading": "(weggefallen)",
      "number": "§ 32",
      "type": "paragraph"
    },
    {
      "breadcrumb": [],
      "file": "paragraphs/0033.md",
      "heading": "Inkrafttreten",
      "number": "§ 33",
      "type": "paragraph"
    }
  ]
}
