{
  "bjnr": "BJNR211590990",
  "schema_version": "v2",
  "sections": [
    {
      "absatz_count": 8,
      "breadcrumb": [
        "Abschnitt I Allgemeine Bestimmungen"
      ],
      "file": "paragraphs/0001.md",
      "heading": "Geltungsbereich",
      "number": "§ 1",
      "type": "paragraph"
    },
    {
      "absatz_count": 5,
      "breadcrumb": [
        "Abschnitt I Allgemeine Bestimmungen"
      ],
      "file": "paragraphs/0002.md",
      "heading": "Begriffsbestimmung",
      "number": "§ 2",
      "type": "paragraph"
    },
    {
      "absatz_count": 5,
      "breadcrumb": [
        "Abschnitt I Allgemeine Bestimmungen"
      ],
      "file": "paragraphs/0002a.md",
      "heading": "Erbengemeinschaft",
      "number": "§ 2a",
      "type": "paragraph"
    },
    {
      "absatz_count": 6,
      "breadcrumb": [
        "Abschnitt I Allgemeine Bestimmungen",
        "Abschnitt II Rückübertragung von Vermögenswerten"
      ],
      "file": "paragraphs/0003.md",
      "heading": "Grundsatz",
      "number": "§ 3",
      "type": "paragraph"
    },
    {
      "absatz_count": 1,
      "breadcrumb": [
        "Abschnitt I Allgemeine Bestimmungen",
        "Abschnitt II Rückübertragung von Vermögenswerten"
      ],
      "file": "paragraphs/0003a.md",
      "heading": "",
      "number": "§ 3a",
      "type": "paragraph"
    },
    {
      "absatz_count": 4,
      "breadcrumb": [
        "Abschnitt I Allgemeine Bestimmungen",
        "Abschnitt II Rückübertragung von Vermögenswerten"
      ],
      "file": "paragraphs/0003b.md",
      "heading": "Gesamtvollstreckungsverfahren, Zwangsversteigerungsverfahren",
      "number": "§ 3b",
      "type": "paragraph"
    },
    {
      "absatz_count": 2,
      "breadcrumb": [
        "Abschnitt I Allgemeine Bestimmungen",
        "Abschnitt II Rückübertragung von Vermögenswerten"
      ],
      "file": "paragraphs/0003c.md",
      "heading": "Erlaubte Veräußerungen",
      "number": "§ 3c",
      "type": "paragraph"
    },
    {
      "absatz_count": 3,
      "breadcrumb": [
        "Abschnitt I Allgemeine Bestimmungen",
        "Abschnitt II Rückübertragung von Vermögenswerten"
      ],
      "file": "paragraphs/0004.md",
      "heading": "Ausschluss der Rückübertragung",
      "number": "§ 4",
      "type": "paragraph"
    },
    {
      "absatz_count": 3,
      "breadcrumb": [
        "Abschnitt I Allgemeine Bestimmungen",
        "Abschnitt II Rückübertragung von Vermögenswerten"
      ],
      "file": "paragraphs/0005.md",
      "heading": "Ausschluss der Rückübertragung von Eigentumsrechten an Grundstücken und Gebäuden",
      "number": "§ 5",
      "type": "paragraph"
    },
    {
      "absatz_count": 15,
      "breadcrumb": [
        "Abschnitt I Allgemeine Bestimmungen",
        "Abschnitt II Rückübertragung von Vermögenswerten"
      ],
      "file": "paragraphs/0006.md",
      "heading": "Rückübertragung von Unternehmen",
      "number": "§ 6",
      "type": "paragraph"
    },
    {
      "absatz_count": 4,
      "breadcrumb": [
        "Abschnitt I Allgemeine Bestimmungen",
        "Abschnitt II Rückübertragung von Vermögenswerten"
      ],
      "file": "paragraphs/0006a.md",
      "heading": "Vorläufige Einweisung",
      "number": "§ 6a",
      "type": "paragraph"
    },
    {
      "absatz_count": 9,
      "breadcrumb": [
        "Abschnitt I Allgemeine Bestimmungen",
        "Abschnitt II Rückübertragung von Vermögenswerten"
      ],
      "file": "paragraphs/0006b.md",
      "heading": "Entflechtung",
      "number": "§ 6b",
      "type": "paragraph"
    },
    {
      "absatz_count": 9,
      "breadcrumb": [
        "Abschnitt I Allgemeine Bestimmungen",
        "Abschnitt II Rückübertragung von Vermögenswerten"
      ],
      "file": "paragraphs/0007.md",
      "heading": "Wertausgleich",
      "number": "§ 7",
      "type": "paragraph"
    },
    {
      "absatz_count": 8,
      "breadcrumb": [
        "Abschnitt I Allgemeine Bestimmungen",
        "Abschnitt II Rückübertragung von Vermögenswerten"
      ],
      "file": "paragraphs/0007a.md",
      "heading": "Gegenleistung",
      "number": "§ 7a",
      "type": "paragraph"
    },
    {
      "absatz_count": 2,
      "breadcrumb": [
        "Abschnitt I Allgemeine Bestimmungen",
        "Abschnitt II Rückübertragung von Vermögenswerten"
      ],
      "file": "paragraphs/0008.md",
      "heading": "Wahlrecht",
      "number": "§ 8",
      "type": "paragraph"
    },
    {
      "absatz_count": 1,
      "breadcrumb": [
        "Abschnitt I Allgemeine Bestimmungen",
        "Abschnitt II Rückübertragung von Vermögenswerten"
      ],
      "file": "paragraphs/0009.md",
      "heading": "",
      "number": "§ 9",
      "type": "paragraph"
    },
    {
      "absatz_count": 1,
      "breadcrumb": [
        "Abschnitt I Allgemeine Bestimmungen",
        "Abschnitt II Rückübertragung von Vermögenswerten"
      ],
      "file": "paragraphs/0010.md",
      "heading": "Bewegliche Sachen",
      "number": "§ 10",
      "type": "paragraph"
    },
    {
      "absatz_count": 6,
      "breadcrumb": [
        "Abschnitt I Allgemeine Bestimmungen",
        "Abschnitt III Aufhebung der staatlichen Verwaltung"
      ],
      "file": "paragraphs/0011.md",
      "heading": "Grundsatz",
      "number": "§ 11",
      "type": "paragraph"
    },
    {
      "absatz_count": 4,
      "breadcrumb": [
        "Abschnitt I Allgemeine Bestimmungen",
        "Abschnitt III Aufhebung der staatlichen Verwaltung"
      ],
      "file": "paragraphs/0011a.md",
      "heading": "Beendigung der staatlichen Verwaltung",
      "number": "§ 11a",
      "type": "paragraph"
    },
    {
      "absatz_count": 3,
      "breadcrumb": [
        "Abschnitt I Allgemeine Bestimmungen",
        "Abschnitt III Aufhebung der staatlichen Verwaltung"
      ],
      "file": "paragraphs/0011b.md",
      "heading": "Vertreter des Eigentümers",
      "number": "§ 11b",
      "type": "paragraph"
    },
    {
      "absatz_count": 1,
      "breadcrumb": [
        "Abschnitt I Allgemeine Bestimmungen",
        "Abschnitt III Aufhebung der staatlichen Verwaltung"
      ],
      "file": "paragraphs/0011c.md",
      "heading": "Genehmigungsvorbehalt",
      "number": "§ 11c",
      "type": "paragraph"
    },
    {
      "absatz_count": 1,
      "breadcrumb": [
        "Abschnitt I Allgemeine Bestimmungen",
        "Abschnitt III Aufhebung der staatlichen Verwaltung"
      ],
      "file": "paragraphs/0012.md",
      "heading": "Staatlich verwaltete Unternehmen und Unternehmensbeteiligungen",
      "number": "§ 12",
      "type": "paragraph"
    },
    {
      "absatz_count": 3,
      "breadcrumb": [
        "Abschnitt I Allgemeine Bestimmungen",
        "Abschnitt III Aufhebung der staatlichen Verwaltung"
      ],
      "file": "paragraphs/0013.md",
      "heading": "Haftung des staatlichen Verwalters",
      "number": "§ 13",
      "type": "paragraph"
    },
    {
      "absatz_count": 2,
      "breadcrumb": [
        "Abschnitt I Allgemeine Bestimmungen",
        "Abschnitt III Aufhebung der staatlichen Verwaltung"
      ],
      "file": "paragraphs/0014.md",
      "heading": "",
      "number": "§ 14",
      "type": "paragraph"
    },
    {
      "absatz_count": 1,
      "breadcrumb": [
        "Abschnitt I Allgemeine Bestimmungen",
        "Abschnitt III Aufhebung der staatlichen Verwaltung"
      ],
      "file": "paragraphs/0014a.md",
      "heading": "Werterhöhungen durch den staatlichen Verwalter",
      "number": "§ 14a",
      "type": "paragraph"
    },
    {
      "absatz_count": 4,
      "breadcrumb": [
        "Abschnitt I Allgemeine Bestimmungen",
        "Abschnitt III Aufhebung der staatlichen Verwaltung"
      ],
      "file": "paragraphs/0015.md",
      "heading": "Befugnisse des staatlichen Verwalters",
      "number": "§ 15",
      "type": "paragraph"
    },
    {
      "absatz_count": 10,
      "breadcrumb": [
        "Abschnitt I Allgemeine Bestimmungen",
        "Abschnitt IV Rechtsverhältnisse zwischen Berechtigten und Dritten"
      ],
      "file": "paragraphs/0016.md",
      "heading": "Übernahme von Rechten und Pflichten",
      "number": "§ 16",
      "type": "paragraph"
    },
    {
      "absatz_count": 1,
      "breadcrumb": [
        "Abschnitt I Allgemeine Bestimmungen",
        "Abschnitt IV Rechtsverhältnisse zwischen Berechtigten und Dritten"
      ],
      "file": "paragraphs/0017.md",
      "heading": "Miet- und Nutzungsrechte",
      "number": "§ 17",
      "type": "paragraph"
    },
    {
      "absatz_count": 8,
      "breadcrumb": [
        "Abschnitt I Allgemeine Bestimmungen",
        "Abschnitt IV Rechtsverhältnisse zwischen Berechtigten und Dritten"
      ],
      "file": "paragraphs/0018.md",
      "heading": "Grundstücksbelastungen",
      "number": "§ 18",
      "type": "paragraph"
    },
    {
      "absatz_count": 1,
      "breadcrumb": [
        "Abschnitt I Allgemeine Bestimmungen",
        "Abschnitt IV Rechtsverhältnisse zwischen Berechtigten und Dritten"
      ],
      "file": "paragraphs/0018a.md",
      "heading": "Rückübertragung des Grundstücks",
      "number": "§ 18a",
      "type": "paragraph"
    },
    {
      "absatz_count": 5,
      "breadcrumb": [
        "Abschnitt I Allgemeine Bestimmungen",
        "Abschnitt IV Rechtsverhältnisse zwischen Berechtigten und Dritten"
      ],
      "file": "paragraphs/0018b.md",
      "heading": "Herausgabe des Ablösebetrages",
      "number": "§ 18b",
      "type": "paragraph"
    },
    {
      "absatz_count": 1,
      "breadcrumb": [
        "Abschnitt I Allgemeine Bestimmungen",
        "Abschnitt IV Rechtsverhältnisse zwischen Berechtigten und Dritten"
      ],
      "file": "paragraphs/0019.md",
      "heading": "",
      "number": "§ 19",
      "type": "paragraph"
    },
    {
      "absatz_count": 9,
      "breadcrumb": [
        "Abschnitt I Allgemeine Bestimmungen",
        "Abschnitt IV Rechtsverhältnisse zwischen Berechtigten und Dritten"
      ],
      "file": "paragraphs/0020.md",
      "heading": "Vorkaufsrecht von Mietern und Nutzern",
      "number": "§ 20",
      "type": "paragraph"
    },
    {
      "absatz_count": 1,
      "breadcrumb": [
        "Abschnitt I Allgemeine Bestimmungen",
        "Abschnitt IV Rechtsverhältnisse zwischen Berechtigten und Dritten"
      ],
      "file": "paragraphs/0020a.md",
      "heading": "Vorkaufsrecht des Berechtigten",
      "number": "§ 20a",
      "type": "paragraph"
    },
    {
      "absatz_count": 5,
      "breadcrumb": [
        "Abschnitt I Allgemeine Bestimmungen",
        "Abschnitt IV Rechtsverhältnisse zwischen Berechtigten und Dritten"
      ],
      "file": "paragraphs/0021.md",
      "heading": "Ersatzgrundstück",
      "number": "§ 21",
      "type": "paragraph"
    },
    {
      "absatz_count": 1,
      "breadcrumb": [
        "Abschnitt I Allgemeine Bestimmungen",
        "Abschnitt V Organisation"
      ],
      "file": "paragraphs/0022.md",
      "heading": "Durchführung der Regelung offener Vermögensfragen",
      "number": "§ 22",
      "type": "paragraph"
    },
    {
      "absatz_count": 2,
      "breadcrumb": [
        "Abschnitt I Allgemeine Bestimmungen",
        "Abschnitt V Organisation"
      ],
      "file": "paragraphs/0023.md",
      "heading": "Landesbehörden",
      "number": "§ 23",
      "type": "paragraph"
    },
    {
      "absatz_count": 1,
      "breadcrumb": [
        "Abschnitt I Allgemeine Bestimmungen",
        "Abschnitt V Organisation"
      ],
      "file": "paragraphs/0024.md",
      "heading": "Untere Landesbehörden",
      "number": "§ 24",
      "type": "paragraph"
    },
    {
      "absatz_count": 2,
      "breadcrumb": [
        "Abschnitt I Allgemeine Bestimmungen",
        "Abschnitt V Organisation"
      ],
      "file": "paragraphs/0025.md",
      "heading": "Landesamt zur Regelung offener Vermögensfragen",
      "number": "§ 25",
      "type": "paragraph"
    },
    {
      "absatz_count": 4,
      "breadcrumb": [
        "Abschnitt I Allgemeine Bestimmungen",
        "Abschnitt V Organisation"
      ],
      "file": "paragraphs/0026.md",
      "heading": "Widerspruchsausschüsse",
      "number": "§ 26",
      "type": "paragraph"
    },
    {
      "absatz_count": 4,
      "breadcrumb": [
        "Abschnitt I Allgemeine Bestimmungen",
        "Abschnitt V Organisation"
      ],
      "file": "paragraphs/0027.md",
      "heading": "Amts- und Rechtshilfe",
      "number": "§ 27",
      "type": "paragraph"
    },
    {
      "absatz_count": 2,
      "breadcrumb": [
        "Abschnitt I Allgemeine Bestimmungen",
        "Abschnitt V Organisation"
      ],
      "file": "paragraphs/0028.md",
      "heading": "Übergangsregelungen",
      "number": "§ 28",
      "type": "paragraph"
    },
    {
      "absatz_count": 4,
      "breadcrumb": [
        "Abschnitt I Allgemeine Bestimmungen",
        "Abschnitt V Organisation"
      ],
      "file": "paragraphs/0029.md",
      "heading": "Bundesamt für zentrale Dienste und offene Vermögensfragen",
      "number": "§ 29",
      "type": "paragraph"
    },
    {
      "absatz_count": 1,
      "breadcrumb": [
        "Abschnitt I Allgemeine Bestimmungen",
        "Abschnitt V Organisation"
      ],
      "file": "paragraphs/0029a.md",
      "heading": "",
      "number": "§ 29a",
      "type": "paragraph"
    },
    {
      "absatz_count": 3,
      "breadcrumb": [
        "Abschnitt I Allgemeine Bestimmungen",
        "Abschnitt VI Verfahrensregelungen"
      ],
      "file": "paragraphs/0030.md",
      "heading": "Antrag",
      "number": "§ 30",
      "type": "paragraph"
    },
    {
      "absatz_count": 4,
      "breadcrumb": [
        "Abschnitt I Allgemeine Bestimmungen",
        "Abschnitt VI Verfahrensregelungen"
      ],
      "file": "paragraphs/0030a.md",
      "heading": "Ausschlussfrist",
      "number": "§ 30a",
      "type": "paragraph"
    },
    {
      "absatz_count": 2,
      "breadcrumb": [
        "Abschnitt I Allgemeine Bestimmungen",
        "Abschnitt VI Verfahrensregelungen"
      ],
      "file": "paragraphs/0030b.md",
      "heading": "Anmeldevermerk",
      "number": "§ 30b",
      "type": "paragraph"
    },
    {
      "absatz_count": 11,
      "breadcrumb": [
        "Abschnitt I Allgemeine Bestimmungen",
        "Abschnitt VI Verfahrensregelungen"
      ],
      "file": "paragraphs/0031.md",
      "heading": "Pflichten der Behörde",
      "number": "§ 31",
      "type": "paragraph"
    },
    {
      "absatz_count": 5,
      "breadcrumb": [
        "Abschnitt I Allgemeine Bestimmungen",
        "Abschnitt VI Verfahrensregelungen"
      ],
      "file": "paragraphs/0032.md",
      "heading": "Beabsichtigte Entscheidung, Auskunft",
      "number": "§ 32",
      "type": "paragraph"
    },
    {
      "absatz_count": 8,
      "breadcrumb": [
        "Abschnitt I Allgemeine Bestimmungen",
        "Abschnitt VI Verfahrensregelungen"
      ],
      "file": "paragraphs/0033.md",
      "heading": "Entscheidung",
      "number": "§ 33",
      "type": "paragraph"
    },
    {
      "absatz_count": 3,
      "breadcrumb": [
        "Abschnitt I Allgemeine Bestimmungen",
        "Abschnitt VI Verfahrensregelungen"
      ],
      "file": "paragraphs/0033a.md",
      "heading": "Fälligkeit, Verzinsung",
      "number": "§ 33a",
      "type": "paragraph"
    },
    {
      "absatz_count": 5,
      "breadcrumb": [
        "Abschnitt I Allgemeine Bestimmungen",
        "Abschnitt VI Verfahrensregelungen"
      ],
      "file": "paragraphs/0034.md",
      "heading": "Eigentumsübergang, Grundbuchberichtigung und Löschung von Vermerken über die staatliche Verwaltung",
      "number": "§ 34",
      "type": "paragraph"
    },
    {
      "absatz_count": 4,
      "breadcrumb": [
        "Abschnitt I Allgemeine Bestimmungen",
        "Abschnitt VI Verfahrensregelungen"
      ],
      "file": "paragraphs/0035.md",
      "heading": "Örtliche Zuständigkeit",
      "number": "§ 35",
      "type": "paragraph"
    },
    {
      "absatz_count": 4,
      "breadcrumb": [
        "Abschnitt I Allgemeine Bestimmungen",
        "Abschnitt VI Verfahrensregelungen"
      ],
      "file": "paragraphs/0036.md",
      "heading": "Widerspruchsverfahren",
      "number": "§ 36",
      "type": "paragraph"
    },
    {
      "absatz_count": 2,
      "breadcrumb": [
        "Abschnitt I Allgemeine Bestimmungen",
        "Abschnitt VI Verfahrensregelungen"
      ],
      "file": "paragraphs/0037.md",
      "heading": "Gerichtliches Verfahren",
      "number": "§ 37",
      "type": "paragraph"
    },
    {
      "absatz_count": 2,
      "breadcrumb": [
        "Abschnitt I Allgemeine Bestimmungen",
        "Abschnitt VI Verfahrensregelungen"
      ],
      "file": "paragraphs/0038.md",
      "heading": "Kosten",
      "number": "§ 38",
      "type": "paragraph"
    },
    {
      "absatz_count": 3,
      "breadcrumb": [
        "Abschnitt I Allgemeine Bestimmungen",
        "Abschnitt VI Verfahrensregelungen"
      ],
      "file": "paragraphs/0038a.md",
      "heading": "Schiedsgericht, Schiedsverfahren",
      "number": "§ 38a",
      "type": "paragraph"
    },
    {
      "absatz_count": 1,
      "breadcrumb": [
        "Abschnitt I Allgemeine Bestimmungen",
        "Abschnitt VI Verfahrensregelungen"
      ],
      "file": "paragraphs/0039.md",
      "heading": "",
      "number": "§ 39",
      "type": "paragraph"
    },
    {
      "absatz_count": 1,
      "breadcrumb": [
        "Abschnitt I Allgemeine Bestimmungen",
        "Abschnitt VI Verfahrensregelungen"
      ],
      "file": "paragraphs/0040.md",
      "heading": "Verordnungsermächtigung",
      "number": "§ 40",
      "type": "paragraph"
    },
    {
      "absatz_count": 7,
      "breadcrumb": [
        "Abschnitt I Allgemeine Bestimmungen",
        "Abschnitt VI Verfahrensregelungen"
      ],
      "file": "paragraphs/0041.md",
      "heading": "Überleitungsvorschrift",
      "number": "§ 41",
      "type": "paragraph"
    }
  ]
}
