{
  "amtabk": null,
  "ausfertigung_datum": "2003-12-10",
  "bjnr": "BJNR247500003",
  "eli": null,
  "gii_slug": "altfabwg",
  "jurabk": "AltfAbwG",
  "schema_version": "v2",
  "section_counts": {
    "paragraph": 4
  },
  "source_hashes": {
    "source_xml_sha256": "6f8e4c30d73f8e4b5aa960533266e32d4e945a74a35b43d2c94868c11e20c155"
  },
  "source_urls": {
    "gii_html": "https://www.gesetze-im-internet.de/altfabwg/",
    "gii_xml_zip": "https://www.gesetze-im-internet.de/altfabwg/xml.zip"
  },
  "stand_datum": null,
  "standangabe": [],
  "title": "Gesetz zur beschleunigten Abwicklung einiger Altforderungen",
  "tooling_version": "gesetze-corpus-tools@0.2.0"
}
