{
  "bjnr": "BJNR004370909",
  "schema_version": "v1",
  "sections": [
    {
      "breadcrumb": [
        "I. Verkehrsvorschriften"
      ],
      "file": "paragraphs/0001.md",
      "heading": "Zulassung",
      "number": "§ 1",
      "type": "paragraph"
    },
    {
      "breadcrumb": [
        "I. Verkehrsvorschriften"
      ],
      "file": "paragraphs/0001a.md",
      "heading": "Kraftfahrzeuge mit hoch- oder vollautomatisierter Fahrfunktion",
      "number": "§ 1a",
      "type": "paragraph"
    },
    {
      "breadcrumb": [
        "I. Verkehrsvorschriften"
      ],
      "file": "paragraphs/0001b.md",
      "heading": "Rechte und Pflichten des Fahrzeugführers bei Nutzung hoch- oder vollautomatisierter Fahrfunktionen",
      "number": "§ 1b",
      "type": "paragraph"
    },
    {
      "breadcrumb": [
        "I. Verkehrsvorschriften"
      ],
      "file": "paragraphs/0001c.md",
      "heading": "Evaluierung",
      "number": "§ 1c",
      "type": "paragraph"
    },
    {
      "breadcrumb": [
        "I. Verkehrsvorschriften"
      ],
      "file": "paragraphs/0001d.md",
      "heading": "Kraftfahrzeuge mit autonomer Fahrfunktion in festgelegten Betriebsbereichen",
      "number": "§ 1d",
      "type": "paragraph"
    },
    {
      "breadcrumb": [
        "I. Verkehrsvorschriften"
      ],
      "file": "paragraphs/0001e.md",
      "heading": "Betrieb von Kraftfahrzeugen mit autonomer Fahrfunktion; Widerspruch und Anfechtungsklage",
      "number": "§ 1e",
      "type": "paragraph"
    },
    {
      "breadcrumb": [
        "I. Verkehrsvorschriften"
      ],
      "file": "paragraphs/0001f.md",
      "heading": "Pflichten der Beteiligten beim Betrieb von Kraftfahrzeugen mit autonomer Fahrfunktion",
      "number": "§ 1f",
      "type": "paragraph"
    },
    {
      "breadcrumb": [
        "I. Verkehrsvorschriften"
      ],
      "file": "paragraphs/0001g.md",
      "heading": "Datenverarbeitung",
      "number": "§ 1g",
      "type": "paragraph"
    },
    {
      "breadcrumb": [
        "I. Verkehrsvorschriften"
      ],
      "file": "paragraphs/0001h.md",
      "heading": "Nachträgliche Aktivierung von automatisierten und autonomen Fahrfunktionen",
      "number": "§ 1h",
      "type": "paragraph"
    },
    {
      "breadcrumb": [
        "I. Verkehrsvorschriften"
      ],
      "file": "paragraphs/0001i.md",
      "heading": "Erprobung von automatisierten und autonomen Fahrfunktionen",
      "number": "§ 1i",
      "type": "paragraph"
    },
    {
      "breadcrumb": [
        "I. Verkehrsvorschriften"
      ],
      "file": "paragraphs/0001j.md",
      "heading": "Verordnungsermächtigung",
      "number": "§ 1j",
      "type": "paragraph"
    },
    {
      "breadcrumb": [
        "I. Verkehrsvorschriften"
      ],
      "file": "paragraphs/0001k.md",
      "heading": "Ausnahmen",
      "number": "§ 1k",
      "type": "paragraph"
    },
    {
      "breadcrumb": [
        "I. Verkehrsvorschriften"
      ],
      "file": "paragraphs/0001l.md",
      "heading": "Evaluierung",
      "number": "§ 1l",
      "type": "paragraph"
    },
    {
      "breadcrumb": [
        "I. Verkehrsvorschriften"
      ],
      "file": "paragraphs/0002.md",
      "heading": "Fahrerlaubnis und Führerschein",
      "number": "§ 2",
      "type": "paragraph"
    },
    {
      "breadcrumb": [
        "I. Verkehrsvorschriften"
      ],
      "file": "paragraphs/0002a.md",
      "heading": "Fahrerlaubnis auf Probe",
      "number": "§ 2a",
      "type": "paragraph"
    },
    {
      "breadcrumb": [
        "I. Verkehrsvorschriften"
      ],
      "file": "paragraphs/0002b.md",
      "heading": "Aufbauseminar bei Zuwiderhandlungen innerhalb der Probezeit",
      "number": "§ 2b",
      "type": "paragraph"
    },
    {
      "breadcrumb": [
        "I. Verkehrsvorschriften"
      ],
      "file": "paragraphs/0002c.md",
      "heading": "Unterrichtung der Fahrerlaubnisbehörden durch das Kraftfahrt-Bundesamt",
      "number": "§ 2c",
      "type": "paragraph"
    },
    {
      "breadcrumb": [
        "I. Verkehrsvorschriften"
      ],
      "file": "paragraphs/0003.md",
      "heading": "Entziehung der Fahrerlaubnis",
      "number": "§ 3",
      "type": "paragraph"
    },
    {
      "breadcrumb": [
        "I. Verkehrsvorschriften"
      ],
      "file": "paragraphs/0004.md",
      "heading": "Fahreignungs-Bewertungssystem",
      "number": "§ 4",
      "type": "paragraph"
    },
    {
      "breadcrumb": [
        "I. Verkehrsvorschriften"
      ],
      "file": "paragraphs/0004a.md",
      "heading": "Fahreignungsseminar",
      "number": "§ 4a",
      "type": "paragraph"
    },
    {
      "breadcrumb": [
        "I. Verkehrsvorschriften"
      ],
      "file": "paragraphs/0004b.md",
      "heading": "Evaluierung",
      "number": "§ 4b",
      "type": "paragraph"
    },
    {
      "breadcrumb": [
        "I. Verkehrsvorschriften"
      ],
      "file": "paragraphs/0005.md",
      "heading": "Verlust von Dokumenten und Kennzeichen",
      "number": "§ 5",
      "type": "paragraph"
    },
    {
      "breadcrumb": [
        "I. Verkehrsvorschriften"
      ],
      "file": "paragraphs/0005a.md",
      "heading": "",
      "number": "§ 5a",
      "type": "paragraph"
    },
    {
      "breadcrumb": [
        "I. Verkehrsvorschriften"
      ],
      "file": "paragraphs/0005b.md",
      "heading": "Unterhaltung der Verkehrszeichen",
      "number": "§ 5b",
      "type": "paragraph"
    },
    {
      "breadcrumb": [
        "I. Verkehrsvorschriften"
      ],
      "file": "paragraphs/0006.md",
      "heading": "Verordnungsermächtigungen",
      "number": "§ 6",
      "type": "paragraph"
    },
    {
      "breadcrumb": [
        "I. Verkehrsvorschriften"
      ],
      "file": "paragraphs/0006a.md",
      "heading": "Gebühren",
      "number": "§ 6a",
      "type": "paragraph"
    },
    {
      "breadcrumb": [
        "I. Verkehrsvorschriften"
      ],
      "file": "paragraphs/0006b.md",
      "heading": "Herstellung, Vertrieb und Ausgabe von Kennzeichen",
      "number": "§ 6b",
      "type": "paragraph"
    },
    {
      "breadcrumb": [
        "I. Verkehrsvorschriften"
      ],
      "file": "paragraphs/0006c.md",
      "heading": "Herstellung, Vertrieb und Ausgabe von Kennzeichenvorprodukten",
      "number": "§ 6c",
      "type": "paragraph"
    },
    {
      "breadcrumb": [
        "I. Verkehrsvorschriften"
      ],
      "file": "paragraphs/0006d.md",
      "heading": "Auskunft und Prüfung",
      "number": "§ 6d",
      "type": "paragraph"
    },
    {
      "breadcrumb": [
        "I. Verkehrsvorschriften"
      ],
      "file": "paragraphs/0006e.md",
      "heading": "Führen von Kraftfahrzeugen in Begleitung",
      "number": "§ 6e",
      "type": "paragraph"
    },
    {
      "breadcrumb": [
        "I. Verkehrsvorschriften"
      ],
      "file": "paragraphs/0006f.md",
      "heading": "Entgelte für Begutachtungsstellen für Fahreignung",
      "number": "§ 6f",
      "type": "paragraph"
    },
    {
      "breadcrumb": [
        "I. Verkehrsvorschriften"
      ],
      "file": "paragraphs/0006g.md",
      "heading": "Internetbasierte Zulassungsverfahren bei Kraftfahrzeugen",
      "number": "§ 6g",
      "type": "paragraph"
    },
    {
      "breadcrumb": [
        "I. Verkehrsvorschriften",
        "II. Haftpflicht"
      ],
      "file": "paragraphs/0007.md",
      "heading": "Haftung des Halters, Schwarzfahrt",
      "number": "§ 7",
      "type": "paragraph"
    },
    {
      "breadcrumb": [
        "I. Verkehrsvorschriften",
        "II. Haftpflicht"
      ],
      "file": "paragraphs/0008.md",
      "heading": "Ausnahmen",
      "number": "§ 8",
      "type": "paragraph"
    },
    {
      "breadcrumb": [
        "I. Verkehrsvorschriften",
        "II. Haftpflicht"
      ],
      "file": "paragraphs/0008a.md",
      "heading": "Entgeltliche Personenbeförderung, Verbot des Haftungsausschlusses",
      "number": "§ 8a",
      "type": "paragraph"
    },
    {
      "breadcrumb": [
        "I. Verkehrsvorschriften",
        "II. Haftpflicht"
      ],
      "file": "paragraphs/0009.md",
      "heading": "Mitverschulden",
      "number": "§ 9",
      "type": "paragraph"
    },
    {
      "breadcrumb": [
        "I. Verkehrsvorschriften",
        "II. Haftpflicht"
      ],
      "file": "paragraphs/0010.md",
      "heading": "Umfang der Ersatzpflicht bei Tötung",
      "number": "§ 10",
      "type": "paragraph"
    },
    {
      "breadcrumb": [
        "I. Verkehrsvorschriften",
        "II. Haftpflicht"
      ],
      "file": "paragraphs/0011.md",
      "heading": "Umfang der Ersatzpflicht bei Körperverletzung",
      "number": "§ 11",
      "type": "paragraph"
    },
    {
      "breadcrumb": [
        "I. Verkehrsvorschriften",
        "II. Haftpflicht"
      ],
      "file": "paragraphs/0012.md",
      "heading": "Höchstbeträge",
      "number": "§ 12",
      "type": "paragraph"
    },
    {
      "breadcrumb": [
        "I. Verkehrsvorschriften",
        "II. Haftpflicht"
      ],
      "file": "paragraphs/0012a.md",
      "heading": "Höchstbeträge bei Beförderung gefährlicher Güter",
      "number": "§ 12a",
      "type": "paragraph"
    },
    {
      "breadcrumb": [
        "I. Verkehrsvorschriften",
        "II. Haftpflicht"
      ],
      "file": "paragraphs/0012b.md",
      "heading": "Nichtanwendbarkeit der Höchstbeträge",
      "number": "§ 12b",
      "type": "paragraph"
    },
    {
      "breadcrumb": [
        "I. Verkehrsvorschriften",
        "II. Haftpflicht"
      ],
      "file": "paragraphs/0013.md",
      "heading": "Geldrente",
      "number": "§ 13",
      "type": "paragraph"
    },
    {
      "breadcrumb": [
        "I. Verkehrsvorschriften",
        "II. Haftpflicht"
      ],
      "file": "paragraphs/0014.md",
      "heading": "Verjährung",
      "number": "§ 14",
      "type": "paragraph"
    },
    {
      "breadcrumb": [
        "I. Verkehrsvorschriften",
        "II. Haftpflicht"
      ],
      "file": "paragraphs/0015.md",
      "heading": "Verwirkung",
      "number": "§ 15",
      "type": "paragraph"
    },
    {
      "breadcrumb": [
        "I. Verkehrsvorschriften",
        "II. Haftpflicht"
      ],
      "file": "paragraphs/0016.md",
      "heading": "Sonstige Gesetze",
      "number": "§ 16",
      "type": "paragraph"
    },
    {
      "breadcrumb": [
        "I. Verkehrsvorschriften",
        "II. Haftpflicht"
      ],
      "file": "paragraphs/0017.md",
      "heading": "Schadensverursachung durch mehrere Kraftfahrzeuge",
      "number": "§ 17",
      "type": "paragraph"
    },
    {
      "breadcrumb": [
        "I. Verkehrsvorschriften",
        "II. Haftpflicht"
      ],
      "file": "paragraphs/0018.md",
      "heading": "Ersatzpflicht des Fahrzeugführers",
      "number": "§ 18",
      "type": "paragraph"
    },
    {
      "breadcrumb": [
        "I. Verkehrsvorschriften",
        "II. Haftpflicht"
      ],
      "file": "paragraphs/0019.md",
      "heading": "Haftung des Halters bei Unfällen mit Anhängern und Gespannen",
      "number": "§ 19",
      "type": "paragraph"
    },
    {
      "breadcrumb": [
        "I. Verkehrsvorschriften",
        "II. Haftpflicht"
      ],
      "file": "paragraphs/0019a.md",
      "heading": "Ersatzpflicht des Führers von Anhängern und Gespannen",
      "number": "§ 19a",
      "type": "paragraph"
    },
    {
      "breadcrumb": [
        "I. Verkehrsvorschriften",
        "II. Haftpflicht"
      ],
      "file": "paragraphs/0020.md",
      "heading": "Örtliche Zuständigkeit",
      "number": "§ 20",
      "type": "paragraph"
    },
    {
      "breadcrumb": [
        "I. Verkehrsvorschriften",
        "III. Straf- und Bußgeldvorschriften"
      ],
      "file": "paragraphs/0021.md",
      "heading": "Fahren ohne Fahrerlaubnis",
      "number": "§ 21",
      "type": "paragraph"
    },
    {
      "breadcrumb": [
        "I. Verkehrsvorschriften",
        "III. Straf- und Bußgeldvorschriften"
      ],
      "file": "paragraphs/0022.md",
      "heading": "Kennzeichenmissbrauch",
      "number": "§ 22",
      "type": "paragraph"
    },
    {
      "breadcrumb": [
        "I. Verkehrsvorschriften",
        "III. Straf- und Bußgeldvorschriften"
      ],
      "file": "paragraphs/0022a.md",
      "heading": "Missbräuchliches Herstellen, Vertreiben oder Ausgeben von Kennzeichen",
      "number": "§ 22a",
      "type": "paragraph"
    },
    {
      "breadcrumb": [
        "I. Verkehrsvorschriften",
        "III. Straf- und Bußgeldvorschriften"
      ],
      "file": "paragraphs/0022b.md",
      "heading": "Missbrauch von Wegstreckenzählern und Geschwindigkeitsbegrenzern",
      "number": "§ 22b",
      "type": "paragraph"
    },
    {
      "breadcrumb": [
        "I. Verkehrsvorschriften",
        "III. Straf- und Bußgeldvorschriften"
      ],
      "file": "paragraphs/0023.md",
      "heading": "(weggefallen)",
      "number": "§ 23",
      "type": "paragraph"
    },
    {
      "breadcrumb": [
        "I. Verkehrsvorschriften",
        "III. Straf- und Bußgeldvorschriften"
      ],
      "file": "paragraphs/0024.md",
      "heading": "Bußgeldvorschriften",
      "number": "§ 24",
      "type": "paragraph"
    },
    {
      "breadcrumb": [
        "I. Verkehrsvorschriften",
        "III. Straf- und Bußgeldvorschriften"
      ],
      "file": "paragraphs/0024a.md",
      "heading": "0,5 Promille-Grenze, Tetrahydrocannabinol-Grenzwert",
      "number": "§ 24a",
      "type": "paragraph"
    },
    {
      "breadcrumb": [
        "I. Verkehrsvorschriften",
        "III. Straf- und Bußgeldvorschriften"
      ],
      "file": "paragraphs/0024b.md",
      "heading": "(weggefallen)",
      "number": "§ 24b",
      "type": "paragraph"
    },
    {
      "breadcrumb": [
        "I. Verkehrsvorschriften",
        "III. Straf- und Bußgeldvorschriften"
      ],
      "file": "paragraphs/0024c.md",
      "heading": "Alkohol- und Cannabisverbot für Fahranfänger und Fahranfängerinnen",
      "number": "§ 24c",
      "type": "paragraph"
    },
    {
      "breadcrumb": [
        "I. Verkehrsvorschriften",
        "III. Straf- und Bußgeldvorschriften"
      ],
      "file": "paragraphs/0025.md",
      "heading": "Fahrverbot",
      "number": "§ 25",
      "type": "paragraph"
    },
    {
      "breadcrumb": [
        "I. Verkehrsvorschriften",
        "III. Straf- und Bußgeldvorschriften"
      ],
      "file": "paragraphs/0025a.md",
      "heading": "Kostentragungspflicht des Halters",
      "number": "§ 25a",
      "type": "paragraph"
    },
    {
      "breadcrumb": [
        "I. Verkehrsvorschriften",
        "III. Straf- und Bußgeldvorschriften"
      ],
      "file": "paragraphs/0026.md",
      "heading": "Zuständige Verwaltungsbehörde; Verjährung",
      "number": "§ 26",
      "type": "paragraph"
    },
    {
      "breadcrumb": [
        "I. Verkehrsvorschriften",
        "III. Straf- und Bußgeldvorschriften"
      ],
      "file": "paragraphs/0026a.md",
      "heading": "Bußgeldkatalog",
      "number": "§ 26a",
      "type": "paragraph"
    },
    {
      "breadcrumb": [
        "I. Verkehrsvorschriften",
        "III. Straf- und Bußgeldvorschriften"
      ],
      "file": "paragraphs/0027.md",
      "heading": "Informationsschreiben",
      "number": "§ 27",
      "type": "paragraph"
    },
    {
      "breadcrumb": [
        "I. Verkehrsvorschriften",
        "IV. Fahreignungsregister"
      ],
      "file": "paragraphs/0028.md",
      "heading": "Führung und Inhalt des Fahreignungsregisters",
      "number": "§ 28",
      "type": "paragraph"
    },
    {
      "breadcrumb": [
        "I. Verkehrsvorschriften",
        "IV. Fahreignungsregister"
      ],
      "file": "paragraphs/0028a.md",
      "heading": "Eintragung beim Abweichen vom Bußgeldkatalog",
      "number": "§ 28a",
      "type": "paragraph"
    },
    {
      "breadcrumb": [
        "I. Verkehrsvorschriften",
        "IV. Fahreignungsregister"
      ],
      "file": "paragraphs/0028b.md",
      "heading": "",
      "number": "§ 28b",
      "type": "paragraph"
    },
    {
      "breadcrumb": [
        "I. Verkehrsvorschriften",
        "IV. Fahreignungsregister"
      ],
      "file": "paragraphs/0029.md",
      "heading": "Tilgung der Eintragungen",
      "number": "§ 29",
      "type": "paragraph"
    },
    {
      "breadcrumb": [
        "I. Verkehrsvorschriften",
        "IV. Fahreignungsregister"
      ],
      "file": "paragraphs/0030.md",
      "heading": "Übermittlung",
      "number": "§ 30",
      "type": "paragraph"
    },
    {
      "breadcrumb": [
        "I. Verkehrsvorschriften",
        "IV. Fahreignungsregister"
      ],
      "file": "paragraphs/0030a.md",
      "heading": "Direkteinstellung und Abruf im automatisierten Verfahren",
      "number": "§ 30a",
      "type": "paragraph"
    },
    {
      "breadcrumb": [
        "I. Verkehrsvorschriften",
        "IV. Fahreignungsregister"
      ],
      "file": "paragraphs/0030b.md",
      "heading": "Automatisiertes Anfrage- und Auskunftsverfahren beim Kraftfahrt-Bundesamt",
      "number": "§ 30b",
      "type": "paragraph"
    },
    {
      "breadcrumb": [
        "I. Verkehrsvorschriften",
        "IV. Fahreignungsregister"
      ],
      "file": "paragraphs/0030c.md",
      "heading": "Verordnungsermächtigungen, Ausführungsvorschriften",
      "number": "§ 30c",
      "type": "paragraph"
    },
    {
      "breadcrumb": [
        "I. Verkehrsvorschriften",
        "V. Fahrzeugregister"
      ],
      "file": "paragraphs/0031.md",
      "heading": "Registerführung und Registerbehörden",
      "number": "§ 31",
      "type": "paragraph"
    },
    {
      "breadcrumb": [
        "I. Verkehrsvorschriften",
        "V. Fahrzeugregister"
      ],
      "file": "paragraphs/0032.md",
      "heading": "Zweckbestimmung der Fahrzeugregister",
      "number": "§ 32",
      "type": "paragraph"
    },
    {
      "breadcrumb": [
        "I. Verkehrsvorschriften",
        "V. Fahrzeugregister"
      ],
      "file": "paragraphs/0033.md",
      "heading": "Inhalt der Fahrzeugregister",
      "number": "§ 33",
      "type": "paragraph"
    },
    {
      "breadcrumb": [
        "I. Verkehrsvorschriften",
        "V. Fahrzeugregister"
      ],
      "file": "paragraphs/0034.md",
      "heading": "Erhebung der Daten",
      "number": "§ 34",
      "type": "paragraph"
    },
    {
      "breadcrumb": [
        "I. Verkehrsvorschriften",
        "V. Fahrzeugregister"
      ],
      "file": "paragraphs/0035.md",
      "heading": "Übermittlung von Fahrzeugdaten und Halterdaten",
      "number": "§ 35",
      "type": "paragraph"
    },
    {
      "breadcrumb": [
        "I. Verkehrsvorschriften",
        "V. Fahrzeugregister"
      ],
      "file": "paragraphs/0036.md",
      "heading": "Abruf im automatisierten Verfahren",
      "number": "§ 36",
      "type": "paragraph"
    },
    {
      "breadcrumb": [
        "I. Verkehrsvorschriften",
        "V. Fahrzeugregister"
      ],
      "file": "paragraphs/0036a.md",
      "heading": "Automatisiertes Anfrage- und Auskunftsverfahren beim Kraftfahrt-Bundesamt",
      "number": "§ 36a",
      "type": "paragraph"
    },
    {
      "breadcrumb": [
        "I. Verkehrsvorschriften",
        "V. Fahrzeugregister"
      ],
      "file": "paragraphs/0036b.md",
      "heading": "Abgleich mit den Sachfahndungsdaten des Bundeskriminalamtes",
      "number": "§ 36b",
      "type": "paragraph"
    },
    {
      "breadcrumb": [
        "I. Verkehrsvorschriften",
        "V. Fahrzeugregister"
      ],
      "file": "paragraphs/0037.md",
      "heading": "Übermittlung von Fahrzeugdaten und Halterdaten an Stellen außerhalb des Geltungsbereiches dieses Gesetzes",
      "number": "§ 37",
      "type": "paragraph"
    },
    {
      "breadcrumb": [
        "I. Verkehrsvorschriften",
        "V. Fahrzeugregister"
      ],
      "file": "paragraphs/0037a.md",
      "heading": "Abruf im automatisierten Verfahren durch Stellen außerhalb des Geltungsbereiches dieses Gesetzes",
      "number": "§ 37a",
      "type": "paragraph"
    },
    {
      "breadcrumb": [
        "I. Verkehrsvorschriften",
        "V. Fahrzeugregister"
      ],
      "file": "paragraphs/0037b.md",
      "heading": "Übermittlung von Fahrzeug- und Halterdaten nach der Richtlinie (EU) 2015/413",
      "number": "§ 37b",
      "type": "paragraph"
    },
    {
      "breadcrumb": [
        "I. Verkehrsvorschriften",
        "V. Fahrzeugregister"
      ],
      "file": "paragraphs/0037c.md",
      "heading": "Übermittlung von Fahrzeugdaten und Halterdaten an die Europäische Kommission",
      "number": "§ 37c",
      "type": "paragraph"
    },
    {
      "breadcrumb": [
        "I. Verkehrsvorschriften",
        "V. Fahrzeugregister"
      ],
      "file": "paragraphs/0038.md",
      "heading": "Übermittlung an und Verwendung durch den Empfänger für wissenschaftliche Zwecke",
      "number": "§ 38",
      "type": "paragraph"
    },
    {
      "breadcrumb": [
        "I. Verkehrsvorschriften",
        "V. Fahrzeugregister"
      ],
      "file": "paragraphs/0038a.md",
      "heading": "Übermittlung an und Verwendung durch den Empfänger für statistische Zwecke",
      "number": "§ 38a",
      "type": "paragraph"
    },
    {
      "breadcrumb": [
        "I. Verkehrsvorschriften",
        "V. Fahrzeugregister"
      ],
      "file": "paragraphs/0038b.md",
      "heading": "Übermittlung an und Verwendung durch den Empfänger für planerische Zwecke",
      "number": "§ 38b",
      "type": "paragraph"
    },
    {
      "breadcrumb": [
        "I. Verkehrsvorschriften",
        "V. Fahrzeugregister"
      ],
      "file": "paragraphs/0039.md",
      "heading": "Übermittlung von Fahrzeugdaten und Halterdaten zur Verfolgung von Rechtsansprüchen",
      "number": "§ 39",
      "type": "paragraph"
    },
    {
      "breadcrumb": [
        "I. Verkehrsvorschriften",
        "V. Fahrzeugregister"
      ],
      "file": "paragraphs/0039a.md",
      "heading": "Auskunft über Daten",
      "number": "§ 39a",
      "type": "paragraph"
    },
    {
      "breadcrumb": [
        "I. Verkehrsvorschriften",
        "V. Fahrzeugregister"
      ],
      "file": "paragraphs/0040.md",
      "heading": "Übermittlung sonstiger Daten",
      "number": "§ 40",
      "type": "paragraph"
    },
    {
      "breadcrumb": [
        "I. Verkehrsvorschriften",
        "V. Fahrzeugregister"
      ],
      "file": "paragraphs/0041.md",
      "heading": "Übermittlungssperren",
      "number": "§ 41",
      "type": "paragraph"
    },
    {
      "breadcrumb": [
        "I. Verkehrsvorschriften",
        "V. Fahrzeugregister"
      ],
      "file": "paragraphs/0042.md",
      "heading": "Datenabgleich zur Beseitigung von Fehlern",
      "number": "§ 42",
      "type": "paragraph"
    },
    {
      "breadcrumb": [
        "I. Verkehrsvorschriften",
        "V. Fahrzeugregister"
      ],
      "file": "paragraphs/0043.md",
      "heading": "Allgemeine Vorschriften für die Datenübermittlung an und die Verarbeitung der Daten durch den Empfänger",
      "number": "§ 43",
      "type": "paragraph"
    },
    {
      "breadcrumb": [
        "I. Verkehrsvorschriften",
        "V. Fahrzeugregister"
      ],
      "file": "paragraphs/0044.md",
      "heading": "Löschung der Daten in den Fahrzeugregistern",
      "number": "§ 44",
      "type": "paragraph"
    },
    {
      "breadcrumb": [
        "I. Verkehrsvorschriften",
        "V. Fahrzeugregister"
      ],
      "file": "paragraphs/0045.md",
      "heading": "Anonymisierte Daten",
      "number": "§ 45",
      "type": "paragraph"
    },
    {
      "breadcrumb": [
        "I. Verkehrsvorschriften",
        "V. Fahrzeugregister"
      ],
      "file": "paragraphs/0046.md",
      "heading": "",
      "number": "§ 46",
      "type": "paragraph"
    },
    {
      "breadcrumb": [
        "I. Verkehrsvorschriften",
        "V. Fahrzeugregister"
      ],
      "file": "paragraphs/0047.md",
      "heading": "Verordnungsermächtigungen, Ausführungsvorschriften",
      "number": "§ 47",
      "type": "paragraph"
    },
    {
      "breadcrumb": [
        "I. Verkehrsvorschriften",
        "VI. Fahrerlaubnisregister"
      ],
      "file": "paragraphs/0048.md",
      "heading": "Registerführung und Registerbehörden",
      "number": "§ 48",
      "type": "paragraph"
    },
    {
      "breadcrumb": [
        "I. Verkehrsvorschriften",
        "VI. Fahrerlaubnisregister"
      ],
      "file": "paragraphs/0049.md",
      "heading": "Zweckbestimmung der Register",
      "number": "§ 49",
      "type": "paragraph"
    },
    {
      "breadcrumb": [
        "I. Verkehrsvorschriften",
        "VI. Fahrerlaubnisregister"
      ],
      "file": "paragraphs/0050.md",
      "heading": "Inhalt der Fahrerlaubnisregister",
      "number": "§ 50",
      "type": "paragraph"
    },
    {
      "breadcrumb": [
        "I. Verkehrsvorschriften",
        "VI. Fahrerlaubnisregister"
      ],
      "file": "paragraphs/0051.md",
      "heading": "Mitteilung an das Zentrale Fahrerlaubnisregister",
      "number": "§ 51",
      "type": "paragraph"
    },
    {
      "breadcrumb": [
        "I. Verkehrsvorschriften",
        "VI. Fahrerlaubnisregister"
      ],
      "file": "paragraphs/0052.md",
      "heading": "Übermittlung",
      "number": "§ 52",
      "type": "paragraph"
    },
    {
      "breadcrumb": [
        "I. Verkehrsvorschriften",
        "VI. Fahrerlaubnisregister"
      ],
      "file": "paragraphs/0053.md",
      "heading": "Direkteinstellung und Abruf im automatisierten Verfahren",
      "number": "§ 53",
      "type": "paragraph"
    },
    {
      "breadcrumb": [
        "I. Verkehrsvorschriften",
        "VI. Fahrerlaubnisregister"
      ],
      "file": "paragraphs/0054.md",
      "heading": "Automatisiertes Mitteilungs-, Anfrage- und Auskunftsverfahren beim Kraftfahrt-Bundesamt",
      "number": "§ 54",
      "type": "paragraph"
    },
    {
      "breadcrumb": [
        "I. Verkehrsvorschriften",
        "VI. Fahrerlaubnisregister"
      ],
      "file": "paragraphs/0055.md",
      "heading": "Übermittlung von Daten an Stellen außerhalb des Geltungsbereiches dieses Gesetzes",
      "number": "§ 55",
      "type": "paragraph"
    },
    {
      "breadcrumb": [
        "I. Verkehrsvorschriften",
        "VI. Fahrerlaubnisregister"
      ],
      "file": "paragraphs/0056.md",
      "heading": "Abruf im automatisierten Verfahren durch Stellen außerhalb des Geltungsbereiches dieses Gesetzes",
      "number": "§ 56",
      "type": "paragraph"
    },
    {
      "breadcrumb": [
        "I. Verkehrsvorschriften",
        "VI. Fahrerlaubnisregister"
      ],
      "file": "paragraphs/0057.md",
      "heading": "Übermittlung an und Verwendung durch den Empfänger für wissenschaftliche, statistische und gesetzgeberische Zwecke",
      "number": "§ 57",
      "type": "paragraph"
    },
    {
      "breadcrumb": [
        "I. Verkehrsvorschriften",
        "VI. Fahrerlaubnisregister"
      ],
      "file": "paragraphs/0058.md",
      "heading": "Auskunft über eigene Daten aus den Registern",
      "number": "§ 58",
      "type": "paragraph"
    },
    {
      "breadcrumb": [
        "I. Verkehrsvorschriften",
        "VI. Fahrerlaubnisregister"
      ],
      "file": "paragraphs/0059.md",
      "heading": "Datenabgleich zur Beseitigung von Fehlern",
      "number": "§ 59",
      "type": "paragraph"
    },
    {
      "breadcrumb": [
        "I. Verkehrsvorschriften",
        "VI. Fahrerlaubnisregister"
      ],
      "file": "paragraphs/0060.md",
      "heading": "Allgemeine Vorschriften für die Datenübermittlung an und die Verarbeitung der Daten durch den Empfänger",
      "number": "§ 60",
      "type": "paragraph"
    },
    {
      "breadcrumb": [
        "I. Verkehrsvorschriften",
        "VI. Fahrerlaubnisregister"
      ],
      "file": "paragraphs/0061.md",
      "heading": "Löschung der Daten",
      "number": "§ 61",
      "type": "paragraph"
    },
    {
      "breadcrumb": [
        "I. Verkehrsvorschriften",
        "VI. Fahrerlaubnisregister"
      ],
      "file": "paragraphs/0062.md",
      "heading": "Register über die Dienstfahrerlaubnisse der Bundeswehr",
      "number": "§ 62",
      "type": "paragraph"
    },
    {
      "breadcrumb": [
        "I. Verkehrsvorschriften",
        "VI. Fahrerlaubnisregister"
      ],
      "file": "paragraphs/0063.md",
      "heading": "Verordnungsermächtigungen, Ausführungsvorschriften",
      "number": "§ 63",
      "type": "paragraph"
    },
    {
      "breadcrumb": [
        "I. Verkehrsvorschriften",
        "VIa. Datenverarbeitung"
      ],
      "file": "paragraphs/0063a.md",
      "heading": "Datenverarbeitung bei Kraftfahrzeugen mit hoch- oder vollautomatisierter Fahrfunktion",
      "number": "§ 63a",
      "type": "paragraph"
    },
    {
      "breadcrumb": [
        "I. Verkehrsvorschriften",
        "VIa. Datenverarbeitung"
      ],
      "file": "paragraphs/0063b.md",
      "heading": "Verordnungsermächtigungen",
      "number": "§ 63b",
      "type": "paragraph"
    },
    {
      "breadcrumb": [
        "I. Verkehrsvorschriften",
        "VIa. Datenverarbeitung"
      ],
      "file": "paragraphs/0063c.md",
      "heading": "Datenverarbeitung im Rahmen der Überprüfung der Einhaltung von Verkehrsbeschränkungen und Verkehrsverboten aufgrund immissionsschutzrechtlicher Vorschriften oder aufgrund straßenverkehrsrechtlicher Vorschriften zum Schutz vor Abgasen",
      "number": "§ 63c",
      "type": "paragraph"
    },
    {
      "breadcrumb": [
        "I. Verkehrsvorschriften",
        "VIa. Datenverarbeitung"
      ],
      "file": "paragraphs/0063d.md",
      "heading": "Informationen an die Halter",
      "number": "§ 63d",
      "type": "paragraph"
    },
    {
      "breadcrumb": [
        "I. Verkehrsvorschriften",
        "VIa. Datenverarbeitung"
      ],
      "file": "paragraphs/0063e.md",
      "heading": "Datenerhebung, Datenspeicherung und Datenverwendung für das Verkehrsmanagement",
      "number": "§ 63e",
      "type": "paragraph"
    },
    {
      "breadcrumb": [
        "I. Verkehrsvorschriften",
        "VIa. Datenverarbeitung"
      ],
      "file": "paragraphs/0063f.md",
      "heading": "Verkehrsunfallforschung, Verordnungsermächtigung",
      "number": "§ 63f",
      "type": "paragraph"
    },
    {
      "breadcrumb": [
        "I. Verkehrsvorschriften",
        "VII. Gemeinsame Vorschriften, Übergangsbestimmungen"
      ],
      "file": "paragraphs/0064.md",
      "heading": "Gemeinsame Vorschriften",
      "number": "§ 64",
      "type": "paragraph"
    },
    {
      "breadcrumb": [
        "I. Verkehrsvorschriften",
        "VII. Gemeinsame Vorschriften, Übergangsbestimmungen"
      ],
      "file": "paragraphs/0065.md",
      "heading": "Übergangsbestimmungen",
      "number": "§ 65",
      "type": "paragraph"
    },
    {
      "breadcrumb": [
        "I. Verkehrsvorschriften",
        "VII. Gemeinsame Vorschriften, Übergangsbestimmungen"
      ],
      "file": "paragraphs/0066.md",
      "heading": "(weggefallen)",
      "number": "§ 66",
      "type": "paragraph"
    },
    {
      "breadcrumb": [
        "I. Verkehrsvorschriften",
        "VII. Gemeinsame Vorschriften, Übergangsbestimmungen"
      ],
      "file": "annexes/0000.md",
      "heading": "(zu § 24a)",
      "number": "Anlage",
      "type": "annex"
    }
  ]
}
